wangfu_autocomplete/__init__.py
wangfu_autocomplete/autocomplete.py
wangfu_autocomplete-0.2.1.dist-info/METADATA
wangfu_autocomplete-0.2.1.dist-info/WHEEL
wangfu_autocomplete-0.2.1.dist-info/entry_points.txt
wangfu_autocomplete-0.2.1.dist-info/top_level.txt
wangfu_autocomplete-0.2.1.dist-info/RECORD
